{
  "version": 3,
  "middleware": {
    "/": {
      "files": [
        "server/edge/chunks/_f9a54c1e._.js",
        "server/edge/chunks/[root-of-the-server]__de110ef0._.js",
        "server/edge/chunks/edge-wrapper_87f1b7d7.js"
      ],
      "name": "middleware",
      "page": "/",
      "matchers": [
        {
          "regexp": "^(?:\\/(_next\\/data\\/[^/]{1,}))?(?:\\/((?!_next|[^?]*\\.(?:html?|css|js(?!on)|jpe?g|webp|png|gif|svg|ttf|woff2?|ico|csv|docx?|xlsx?|zip|webmanifest)).*))(\\\\.json)?[\\/#\\?]?$",
          "originalSource": "/((?!_next|[^?]*\\.(?:html?|css|js(?!on)|jpe?g|webp|png|gif|svg|ttf|woff2?|ico|csv|docx?|xlsx?|zip|webmanifest)).*)"
        },
        {
          "regexp": "^(?:\\/(_next\\/data\\/[^/]{1,}))?(?:\\/(api|trpc))(.*)(\\\\.json)?[\\/#\\?]?$",
          "originalSource": "/(api|trpc)(.*)"
        }
      ],
      "wasm": [],
      "assets": [],
      "env": {
        "__NEXT_BUILD_ID": "development",
        "NEXT_SERVER_ACTIONS_ENCRYPTION_KEY": "dmMKy/N73qEHg92LOpWYvxL0M6E1F/+HoAAfOm4jFZ8=",
        "__NEXT_PREVIEW_MODE_ID": "4a87327a88ebf42849663c02935e267d",
        "__NEXT_PREVIEW_MODE_ENCRYPTION_KEY": "3be9f9592520a515e48341dc1ad4e708a4a289d4bc2bbc9f4fefef3b7b8bfeee",
        "__NEXT_PREVIEW_MODE_SIGNING_KEY": "c9a842058197d03deed9d1889ef88ac9f98f4f20058d15367160d5746f557fd7"
      }
    }
  },
  "sortedMiddleware": [
    "/"
  ],
  "functions": {}
}